LICENCE.txt
MANIFEST.in
README.txt
setup.py
albalacalculator.egg-info/PKG-INFO
albalacalculator.egg-info/SOURCES.txt
albalacalculator.egg-info/dependency_links.txt
albalacalculator.egg-info/top_level.txt
my_calc/__init__.py