Metadata-Version: 2.1
Name: albalacalculator
Version: 0.0.1
Summary: A very basic calculator
Home-page: UNKNOWN
Author: Alex Georgiev
Author-email: aagueorguiev@gmai.com
License: MIT
Keywords: calculator
Platform: UNKNOWN
Classifier: Development Status :: 5 - Production/Stable
Classifier: Intended Audience :: Education
Classifier: License :: OSI Approved :: MIT License
Classifier: Operating System :: Microsoft :: Windows
Classifier: Programming Language :: Python
License-File: LICENCE.txt
